[{"name":"red","r":255,"g":0,"b":0},{"name":"orange","r":255,"g":128,"b":64},{"name":"yellow","r":255,"g":255,"b":0},{"name":"green","r":0,"g":255,"b":0},{"name":"cyan","r":0,"g":255,"b":255},{"name":"blue","r":0,"g":0,"b":255},{"name":"purple","r":128,"g":0,"b":128},{"name":"black","r":0,"g":0,"b":0},{"name":"gray","r":192,"g":192,"b":192},{"name":"gray","r":128,"g":128,"b":128},{"name":"white","r":255,"g":255,"b":255},{"name":"blue","r":0,"g":0,"b":160},{"name":"cyan","r":173,"g":216,"b":230},{"name":"pink","r":255,"g":0,"b":255},{"name":"red","r":165,"g":42,"b":42},{"name":"red","r":128,"g":0,"b":0},{"name":"green","r":0,"g":128,"b":0},{"name":"green","r":128,"g":128,"b":0},{"name":"blue","r":36,"g":117,"b":130},{"name":"brown","r":85,"g":72,"b":74},{"name":"green","r":140,"g":206,"b":81},{"name":"green","r":140,"g":179,"b":13},{"name":"green","r":23,"g":194,"b":30},{"name":"purple","r":126,"g":55,"b":126},{"name":"red","r":247,"g":74,"b":74},{"name":"blue","r":5,"g":38,"b":74},{"name":"purple","r":163,"g":20,"b":164},{"name":"green","r":30,"g":182,"b":78},{"name":"purple","r":118,"g":93,"b":136},{"name":"purple","r":122,"g":65,"b":188},{"name":"blue","r":84,"g":131,"b":242},{"name":"yellow","r":205,"g":209,"b":117},{"name":"cyan","r":140,"g":239,"b":211},{"name":"brown","r":194,"g":163,"b":0},{"name":"red","r":164,"g":65,"b":48},{"name":"cyan","r":175,"g":231,"b":167},{"name":"yellow","r":187,"g":154,"b":13},{"name":"pink","r":218,"g":197,"b":196},{"name":"red","r":221,"g":25,"b":3},{"name":"purple","r":97,"g":29,"b":179},{"name":"purple","r":103,"g":47,"b":244},{"name":"red","r":188,"g":15,"b":15},{"name":"pink","r":237,"g":144,"b":179},{"name":"black","r":65,"g":36,"b":2},{"name":"green","r":180,"g":189,"b":69},{"name":"green","r":199,"g":207,"b":30},{"name":"red","r":161,"g":37,"b":77},{"name":"green","r":98,"g":148,"b":94},{"name":"green","r":66,"g":203,"b":19},{"name":"green","r":26,"g":175,"b":40},{"name":"gray","r":173,"g":173,"b":118},{"name":"purple","r":93,"g":3,"b":204},{"name":"purple","r":163,"g":51,"b":107},{"name":"green","r":171,"g":171,"b":41},{"name":"purple","r":85,"g":45,"b":83},{"name":"pink","r":230,"g":165,"b":136},{"name":"green","r":221,"g":227,"b":141},{"name":"purple","r":187,"g":59,"b":146},{"name":"brown","r":166,"g":106,"b":103},{"name":"cyan","r":145,"g":237,"b":223},{"name":"cyan","r":66,"g":254,"b":211},{"name":"pink","r":240,"g":75,"b":225},{"name":"green","r":10,"g":146,"b":120},{"name":"pink","r":228,"g":9,"b":200},{"name":"cyan","r":55,"g":225,"b":245},{"name":"brown","r":214,"g":162,"b":39},{"name":"orange","r":243,"g":177,"b":34},{"name":"brown","r":201,"g":169,"b":128},{"name":"blue","r":84,"g":130,"b":230},{"name":"cyan","r":8,"g":225,"b":202},{"name":"green","r":13,"g":249,"b":22},{"name":"cyan","r":9,"g":201,"b":233},{"name":"brown","r":89,"g":28,"b":48},{"name":"purple","r":166,"g":105,"b":192},{"name":"green","r":28,"g":215,"b":14},{"name":"purple","r":114,"g":77,"b":105},{"name":"pink","r":213,"g":129,"b":232},{"name":"red","r":175,"g":18,"b":66},{"name":"gray","r":151,"g":118,"b":134},{"name":"brown","r":205,"g":172,"b":68},{"name":"cyan","r":58,"g":178,"b":209},{"name":"blue","r":5,"g":116,"b":185},{"name":"brown","r":106,"g":37,"b":20},{"name":"blue","r":50,"g":83,"b":132},{"name":"purple","r":168,"g":56,"b":205},{"name":"purple","r":216,"g":68,"b":128},{"name":"blue","r":40,"g":22,"b":170},{"name":"brown","r":106,"g":28,"b":33},{"name":"green","r":117,"g":179,"b":131},{"name":"pink","r":218,"g":22,"b":153},{"name":"purple","r":141,"g":21,"b":197},{"name":"blue","r":5,"g":2,"b":101},{"name":"blue","r":17,"g":7,"b":87},{"name":"green","r":214,"g":222,"b":66},{"name":"green","r":62,"g":188,"b":7},{"name":"green","r":12,"g":147,"b":9},{"name":"blue","r":58,"g":78,"b":145},{"name":"blue","r":17,"g":33,"b":101},{"name":"pink","r":198,"g":151,"b":195},{"name":"green","r":69,"g":250,"b":175},{"name":"red","r":218,"g":44,"b":134},{"name":"brown","r":190,"g":87,"b":25},{"name":"green","r":102,"g":227,"b":173},{"name":"red","r":251,"g":25,"b":76},{"name":"green","r":22,"g":219,"b":206},{"name":"brown","r":226,"g":208,"b":165},{"name":"brown","r":90,"g":43,"b":20},{"name":"brown","r":218,"g":172,"b":35},{"name":"pink","r":208,"g":115,"b":196},{"name":"pink","r":255,"g":53,"b":232},{"name":"blue","r":98,"g":113,"b":174},{"name":"purple","r":179,"g":141,"b":238},{"name":"green","r":3,"g":87,"b":56}]